vital_llm_reasoner/__init__.py
vital_llm_reasoner/attention/__init__.py
vital_llm_reasoner/attention/ensemble_attention.py
vital_llm_reasoner/config/__init__.py
vital_llm_reasoner/config/reasoner_config.py
vital_llm_reasoner/ensemble/__init__.py
vital_llm_reasoner/ensemble/command/__init__.py
vital_llm_reasoner/ensemble/command/command_parser.py
vital_llm_reasoner/ensemble/member/__init__.py
vital_llm_reasoner/ensemble/member/answer.py
vital_llm_reasoner/ensemble/member/code_executor_member.py
vital_llm_reasoner/ensemble/member/critique_member.py
vital_llm_reasoner/ensemble/member/ensemble_member.py
vital_llm_reasoner/ensemble/member/evidence_extraction_member.py
vital_llm_reasoner/ensemble/member/filesystem_member.py
vital_llm_reasoner/ensemble/member/gdrive_member.py
vital_llm_reasoner/ensemble/member/github_member.py
vital_llm_reasoner/ensemble/member/inquiry.py
vital_llm_reasoner/ensemble/member/kgraph_document_member.py
vital_llm_reasoner/ensemble/member/kgraph_query_member.py
vital_llm_reasoner/ensemble/member/kgraph_traverse_member.py
vital_llm_reasoner/ensemble/member/llm_member.py
vital_llm_reasoner/ensemble/member/logic_query_member.py
vital_llm_reasoner/ensemble/member/reasoning_member.py
vital_llm_reasoner/ensemble/member/task_tag.py
vital_llm_reasoner/ensemble/member/web_extract_member.py
vital_llm_reasoner/ensemble/member/web_search_member.py
vital_llm_reasoner/ensemble/member/wikidata_search_member.py
vital_llm_reasoner/ensemble/member/wikidata_traverse_member.py
vital_llm_reasoner/ensemble/process/__init__.py
vital_llm_reasoner/ensemble/process/logits_default_processor.py
vital_llm_reasoner/ensemble/process/orchestrator.py
vital_llm_reasoner/ensemble/process/process_graph.py
vital_llm_reasoner/ensemble/process/token_processor.py
vital_llm_reasoner/ensemble/task/__init__.py
vital_llm_reasoner/ensemble/task/ensemble_task.py
vital_llm_reasoner/kgraph/__init__.py
vital_llm_reasoner/kgraph/kgraph_query_parser.py
vital_llm_reasoner/reasoner/__init__.py
vital_llm_reasoner-0.0.10.dist-info/LICENSE
vital_llm_reasoner-0.0.10.dist-info/METADATA
vital_llm_reasoner-0.0.10.dist-info/WHEEL
vital_llm_reasoner-0.0.10.dist-info/top_level.txt
vital_llm_reasoner-0.0.10.dist-info/RECORD
