Metadata-Version: 2.1
Name: vital-llm-reasoner
Version: 0.0.10
Summary: Vital LLM Reasoner
Home-page: https://github.com/vital-ai/vital-llm-reasoner
Author: Marc Hadfield
Author-email: marc@vital.ai
License: Apache License 2.0
Classifier: Programming Language :: Python :: 3.11
Classifier: License :: OSI Approved :: Apache Software License
Classifier: Operating System :: OS Independent
Requires-Python: >=3.11
License-File: LICENSE
Requires-Dist: vital-agentbox>=0.0.2
Requires-Dist: kgraphlang>=0.0.9
Requires-Dist: lark
Requires-Dist: langchain-openai==0.2.1
Requires-Dist: openai==1.100.1
Requires-Dist: langchain==0.3.9
Requires-Dist: langchain-openai
Requires-Dist: langchain-core
Requires-Dist: pyahocorasick>=2.1.0
Requires-Dist: numpy>=1.21.0
Requires-Dist: torch
Requires-Dist: transformers
Requires-Dist: sentencepiece
Requires-Dist: tqdm
Requires-Dist: nltk
Requires-Dist: bs4
Requires-Dist: pdfplumber
Requires-Dist: scrapy
Requires-Dist: scrapy-playwright
Requires-Dist: playwright
Requires-Dist: markitdown
Requires-Dist: black
Requires-Dist: google-search-results>=2.4.2
Requires-Dist: requests
Requires-Dist: vital-logic>=0.1.0
Requires-Dist: vital-ai-vitalsigns>=0.1.27
Requires-Dist: vital-ai-domain>=0.1.4
Requires-Dist: pyyaml
Requires-Dist: vital-ai-haley-kg>=0.1.24
Requires-Dist: kgraphservice>=0.0.6
Requires-Dist: sentence-transformers>=3.3.1
Requires-Dist: llama-cpp-python>=0.2.20
Provides-Extra: llamacpp
Requires-Dist: llama-cpp-python>=0.2.20; extra == "llamacpp"
Provides-Extra: vllm
Requires-Dist: vllm>=0.7.0; extra == "vllm"
